{
  "deck_title": ["Sixpack (Dark multicolor scheme) (v0.8.0-3)"],
  "deck_filename": ["sixpack3"],
  "rank_symbols": ["N,A,2,3,4,5"],
  "suit_symbols": ["♥,♠,♣,♦,🌞,🌜,꩜"],
  "header_font": ["Noto Sans"],
  "rank_symbols_font": ["Noto Sans"],
  "suit_symbols_font": ["Noto Emoji"],
  "suit_symbols_scale": ["0.9,0.9,0.9,0.9,0.7,0.7,1.1,1.2"],
  "font": ["Noto Sans Symbols"],
  "suit_colors": ["darkred,black,darkgreen,darkblue,orange3,purple,tan4"],
  "background_colors": ["seashell3"],
  "shape.chip": ["5"]
}
